{"cameraMode":{"drawMode":0,"name":"Shaded","section":"Shading Mode"},"sceneLighting":true,"audioPlay":false,"sceneViewState":{"m_AlwaysRefresh":false,"showFog":true,"showSkybox":true,"showFlares":true,"showImageEffects":true,"showParticleSystems":true,"showVisualEffectGraphs":true,"m_FxEnabled":true},"in2DMode":false,"pivot":{"x":388.1594543457031,"y":190.535888671875,"z":35.31280517578125},"rotation":{"x":-0.18670779466629029,"y":0.002060279482975602,"z":-0.0003918200673069805,"w":-0.9824139475822449},"size":237.39056396484376,"orthographic":false}